[
  {
    "n": "Town Hall",
    "la": -33.873,
    "lo": 151.2069,
    "m": 0
  },
  {
    "n": "Wynyard",
    "la": -33.866,
    "lo": 151.206,
    "m": 1
  },
  {
    "n": "Martin Place",
    "la": -33.8688,
    "lo": 151.2113,
    "m": 2
  },
  {
    "n": "St James",
    "la": -33.8687,
    "lo": 151.2103,
    "m": 2
  },
  {
    "n": "Museum",
    "la": -33.8761,
    "lo": 151.2087,
    "m": 2
  },
  {
    "n": "Central",
    "la": -33.8832,
    "lo": 151.207,
    "m": 2
  },
  {
    "n": "Circular Quay",
    "la": -33.8614,
    "lo": 151.2113,
    "m": 2
  },
  {
    "n": "Milsons Point",
    "la": -33.8467,
    "lo": 151.2107,
    "m": 4
  },
  {
    "n": "North Sydney",
    "la": -33.839,
    "lo": 151.2069,
    "m": 6
  },
  {
    "n": "Waverton",
    "la": -33.8378,
    "lo": 151.201,
    "m": 8
  },
  {
    "n": "Wollstonecraft",
    "la": -33.8316,
    "lo": 151.2009,
    "m": 10
  },
  {
    "n": "St Leonards",
    "la": -33.8226,
    "lo": 151.1958,
    "m": 12
  },
  {
    "n": "Artarmon",
    "la": -33.8089,
    "lo": 151.1858,
    "m": 14
  },
  {
    "n": "Chatswood",
    "la": -33.7967,
    "lo": 151.1827,
    "m": 16
  },
  {
    "n": "Roseville",
    "la": -33.7822,
    "lo": 151.1797,
    "m": 18
  },
  {
    "n": "Lindfield",
    "la": -33.7768,
    "lo": 151.1719,
    "m": 20
  },
  {
    "n": "Killara",
    "la": -33.7659,
    "lo": 151.1638,
    "m": 22
  },
  {
    "n": "Gordon",
    "la": -33.7559,
    "lo": 151.1547,
    "m": 24
  },
  {
    "n": "Pymble",
    "la": -33.744,
    "lo": 151.1428,
    "m": 26
  },
  {
    "n": "Turramurra",
    "la": -33.7308,
    "lo": 151.1297,
    "m": 28
  },
  {
    "n": "Warrawee",
    "la": -33.7193,
    "lo": 151.1232,
    "m": 30
  },
  {
    "n": "Wahroonga",
    "la": -33.7155,
    "lo": 151.1167,
    "m": 32
  },
  {
    "n": "Waitara",
    "la": -33.7115,
    "lo": 151.1083,
    "m": 34
  },
  {
    "n": "Hornsby",
    "la": -33.7041,
    "lo": 151.0991,
    "m": 36
  },
  {
    "n": "Asquith",
    "la": -33.689,
    "lo": 151.1086,
    "m": 38
  },
  {
    "n": "Mt Colah",
    "la": -33.6712,
    "lo": 151.1115,
    "m": 42
  },
  {
    "n": "Berowra",
    "la": -33.6286,
    "lo": 151.1532,
    "m": 48
  },
  {
    "n": "Redfern",
    "la": -33.892,
    "lo": 151.1985,
    "m": 3
  },
  {
    "n": "Macdonaldtown",
    "la": -33.8966,
    "lo": 151.1898,
    "m": 5
  },
  {
    "n": "Newtown",
    "la": -33.8966,
    "lo": 151.1796,
    "m": 6
  },
  {
    "n": "Stanmore",
    "la": -33.8924,
    "lo": 151.1641,
    "m": 7
  },
  {
    "n": "Petersham",
    "la": -33.8949,
    "lo": 151.1564,
    "m": 8
  },
  {
    "n": "Lewisham",
    "la": -33.8972,
    "lo": 151.149,
    "m": 9
  },
  {
    "n": "Summer Hill",
    "la": -33.8911,
    "lo": 151.1393,
    "m": 10
  },
  {
    "n": "Ashfield",
    "la": -33.8881,
    "lo": 151.1259,
    "m": 11
  },
  {
    "n": "Croydon",
    "la": -33.8839,
    "lo": 151.1135,
    "m": 12
  },
  {
    "n": "Burwood",
    "la": -33.8784,
    "lo": 151.1041,
    "m": 13
  },
  {
    "n": "Strathfield",
    "la": -33.8714,
    "lo": 151.0936,
    "m": 15
  },
  {
    "n": "Homebush",
    "la": -33.8643,
    "lo": 151.0848,
    "m": 17
  },
  {
    "n": "Flemington",
    "la": -33.8631,
    "lo": 151.066,
    "m": 18
  },
  {
    "n": "Lidcombe",
    "la": -33.8657,
    "lo": 151.0407,
    "m": 20
  },
  {
    "n": "Berala",
    "la": -33.8754,
    "lo": 151.0341,
    "m": 22
  },
  {
    "n": "Regents Park",
    "la": -33.8866,
    "lo": 151.0259,
    "m": 23
  },
  {
    "n": "Auburn",
    "la": -33.8489,
    "lo": 151.0335,
    "m": 22
  },
  {
    "n": "Clyde",
    "la": -33.8329,
    "lo": 151.0245,
    "m": 24
  },
  {
    "n": "Granville",
    "la": -33.8326,
    "lo": 151.0123,
    "m": 25
  },
  {
    "n": "Harris Park",
    "la": -33.8205,
    "lo": 151.0095,
    "m": 27
  },
  {
    "n": "Parramatta",
    "la": -33.817,
    "lo": 151.0058,
    "m": 28
  },
  {
    "n": "Westmead",
    "la": -33.8084,
    "lo": 150.9889,
    "m": 30
  },
  {
    "n": "Wentworthville",
    "la": -33.8077,
    "lo": 150.9722,
    "m": 32
  },
  {
    "n": "Pendle Hill",
    "la": -33.8013,
    "lo": 150.9554,
    "m": 34
  },
  {
    "n": "Toongabbie",
    "la": -33.7889,
    "lo": 150.9489,
    "m": 36
  },
  {
    "n": "Seven Hills",
    "la": -33.7745,
    "lo": 150.9359,
    "m": 38
  },
  {
    "n": "Blacktown",
    "la": -33.7691,
    "lo": 150.9075,
    "m": 42
  },
  {
    "n": "Doonside",
    "la": -33.7677,
    "lo": 150.8723,
    "m": 45
  },
  {
    "n": "Rooty Hill",
    "la": -33.771,
    "lo": 150.8417,
    "m": 48
  },
  {
    "n": "Mt Druitt",
    "la": -33.7704,
    "lo": 150.8217,
    "m": 50
  },
  {
    "n": "St Marys",
    "la": -33.7683,
    "lo": 150.7748,
    "m": 55
  },
  {
    "n": "Werrington",
    "la": -33.7589,
    "lo": 150.7521,
    "m": 57
  },
  {
    "n": "Kingswood",
    "la": -33.7556,
    "lo": 150.7177,
    "m": 58
  },
  {
    "n": "Penrith",
    "la": -33.7517,
    "lo": 150.6963,
    "m": 60
  },
  {
    "n": "Emu Plains",
    "la": -33.746,
    "lo": 150.6664,
    "m": 64
  },
  {
    "n": "Cabramatta",
    "la": -33.8954,
    "lo": 150.9355,
    "m": 34
  },
  {
    "n": "Canley Vale",
    "la": -33.8896,
    "lo": 150.9469,
    "m": 32
  },
  {
    "n": "Fairfield",
    "la": -33.8732,
    "lo": 150.956,
    "m": 30
  },
  {
    "n": "Yennora",
    "la": -33.8606,
    "lo": 150.9621,
    "m": 28
  },
  {
    "n": "Guildford",
    "la": -33.8554,
    "lo": 150.9747,
    "m": 26
  },
  {
    "n": "Merrylands",
    "la": -33.8366,
    "lo": 150.9856,
    "m": 24
  },
  {
    "n": "Liverpool",
    "la": -33.9202,
    "lo": 150.9265,
    "m": 38
  },
  {
    "n": "Warwick Farm",
    "la": -33.9128,
    "lo": 150.9377,
    "m": 36
  },
  {
    "n": "Casula",
    "la": -33.9542,
    "lo": 150.9046,
    "m": 40
  },
  {
    "n": "Glenfield",
    "la": -33.967,
    "lo": 150.8902,
    "m": 42
  },
  {
    "n": "Edmondson Park",
    "la": -33.971,
    "lo": 150.858,
    "m": 47
  },
  {
    "n": "Leppington",
    "la": -33.992,
    "lo": 150.8101,
    "m": 50
  },
  {
    "n": "Erskineville",
    "la": -33.9019,
    "lo": 151.1849,
    "m": 4
  },
  {
    "n": "St Peters",
    "la": -33.9095,
    "lo": 151.1816,
    "m": 6
  },
  {
    "n": "Sydenham",
    "la": -33.9159,
    "lo": 151.1664,
    "m": 9
  },
  {
    "n": "Marrickville",
    "la": -33.9094,
    "lo": 151.1542,
    "m": 12
  },
  {
    "n": "Dulwich Hill",
    "la": -33.9043,
    "lo": 151.1399,
    "m": 14
  },
  {
    "n": "Hurlstone Park",
    "la": -33.9094,
    "lo": 151.1338,
    "m": 16
  },
  {
    "n": "Canterbury",
    "la": -33.9143,
    "lo": 151.1188,
    "m": 18
  },
  {
    "n": "Campsie",
    "la": -33.912,
    "lo": 151.1023,
    "m": 20
  },
  {
    "n": "Belmore",
    "la": -33.9201,
    "lo": 151.0879,
    "m": 23
  },
  {
    "n": "Lakemba",
    "la": -33.9211,
    "lo": 151.0758,
    "m": 25
  },
  {
    "n": "Wiley Park",
    "la": -33.9209,
    "lo": 151.0623,
    "m": 27
  },
  {
    "n": "Punchbowl",
    "la": -33.9265,
    "lo": 151.0508,
    "m": 29
  },
  {
    "n": "Bankstown",
    "la": -33.9183,
    "lo": 151.0349,
    "m": 32
  },
  {
    "n": "Yagoona",
    "la": -33.9007,
    "lo": 151.0345,
    "m": 34
  },
  {
    "n": "Birrong",
    "la": -33.8895,
    "lo": 151.0341,
    "m": 36
  },
  {
    "n": "Kings Cross",
    "la": -33.874,
    "lo": 151.2225,
    "m": 4
  },
  {
    "n": "Edgecliff",
    "la": -33.8788,
    "lo": 151.2371,
    "m": 6
  },
  {
    "n": "Bondi Junction",
    "la": -33.8922,
    "lo": 151.2474,
    "m": 9
  },
  {
    "n": "Tempe",
    "la": -33.9211,
    "lo": 151.162,
    "m": 11
  },
  {
    "n": "Wolli Creek",
    "la": -33.9292,
    "lo": 151.1543,
    "m": 13
  },
  {
    "n": "Arncliffe",
    "la": -33.9359,
    "lo": 151.1471,
    "m": 16
  },
  {
    "n": "Banksia",
    "la": -33.943,
    "lo": 151.1419,
    "m": 17
  },
  {
    "n": "Rockdale",
    "la": -33.9518,
    "lo": 151.1369,
    "m": 19
  },
  {
    "n": "Kogarah",
    "la": -33.9628,
    "lo": 151.1322,
    "m": 21
  },
  {
    "n": "Carlton",
    "la": -33.9684,
    "lo": 151.1259,
    "m": 22
  },
  {
    "n": "Allawah",
    "la": -33.9711,
    "lo": 151.118,
    "m": 23
  },
  {
    "n": "Hurstville",
    "la": -33.9676,
    "lo": 151.1027,
    "m": 25
  },
  {
    "n": "Penshurst",
    "la": -33.9655,
    "lo": 151.0867,
    "m": 27
  },
  {
    "n": "Mortdale",
    "la": -33.97,
    "lo": 151.0826,
    "m": 29
  },
  {
    "n": "Oatley",
    "la": -33.9826,
    "lo": 151.0793,
    "m": 31
  },
  {
    "n": "Como",
    "la": -34.0011,
    "lo": 151.0717,
    "m": 33
  },
  {
    "n": "Jannali",
    "la": -34.014,
    "lo": 151.0626,
    "m": 35
  },
  {
    "n": "Sutherland",
    "la": -34.0306,
    "lo": 151.0577,
    "m": 38
  },
  {
    "n": "Loftus",
    "la": -34.0479,
    "lo": 151.0552,
    "m": 40
  },
  {
    "n": "Engadine",
    "la": -34.068,
    "lo": 151.0136,
    "m": 43
  },
  {
    "n": "Heathcote",
    "la": -34.0859,
    "lo": 151.0098,
    "m": 46
  },
  {
    "n": "Waterfall",
    "la": -34.1407,
    "lo": 150.9985,
    "m": 52
  },
  {
    "n": "Kirrawee",
    "la": -34.0353,
    "lo": 151.0779,
    "m": 41
  },
  {
    "n": "Gymea",
    "la": -34.0353,
    "lo": 151.0863,
    "m": 43
  },
  {
    "n": "Miranda",
    "la": -34.0349,
    "lo": 151.0998,
    "m": 45
  },
  {
    "n": "Caringbah",
    "la": -34.0392,
    "lo": 151.1235,
    "m": 47
  },
  {
    "n": "Cronulla",
    "la": -34.057,
    "lo": 151.1513,
    "m": 50
  },
  {
    "n": "Green Square",
    "la": -33.9069,
    "lo": 151.1986,
    "m": 6
  },
  {
    "n": "Mascot",
    "la": -33.923,
    "lo": 151.1944,
    "m": 8
  },
  {
    "n": "Domestic Airport",
    "la": -33.9357,
    "lo": 151.181,
    "m": 11
  },
  {
    "n": "Intl Airport",
    "la": -33.9333,
    "lo": 151.1654,
    "m": 13
  },
  {
    "n": "Turrella",
    "la": -33.9352,
    "lo": 151.1438,
    "m": 15
  },
  {
    "n": "Bardwell Park",
    "la": -33.9382,
    "lo": 151.1335,
    "m": 17
  },
  {
    "n": "Bexley North",
    "la": -33.9447,
    "lo": 151.1207,
    "m": 19
  },
  {
    "n": "Kingsgrove",
    "la": -33.9472,
    "lo": 151.1056,
    "m": 21
  },
  {
    "n": "Beverly Hills",
    "la": -33.9479,
    "lo": 151.0827,
    "m": 23
  },
  {
    "n": "Narwee",
    "la": -33.9479,
    "lo": 151.0712,
    "m": 25
  },
  {
    "n": "Riverwood",
    "la": -33.9527,
    "lo": 151.0537,
    "m": 27
  },
  {
    "n": "Padstow",
    "la": -33.9523,
    "lo": 151.0319,
    "m": 29
  },
  {
    "n": "Revesby",
    "la": -33.9505,
    "lo": 151.0152,
    "m": 31
  },
  {
    "n": "Panania",
    "la": -33.9505,
    "lo": 150.9975,
    "m": 33
  },
  {
    "n": "East Hills",
    "la": -33.9609,
    "lo": 150.9879,
    "m": 35
  },
  {
    "n": "Holsworthy",
    "la": -33.9568,
    "lo": 150.955,
    "m": 38
  },
  {
    "n": "Macquarie Fields",
    "la": -33.9907,
    "lo": 150.8961,
    "m": 42
  },
  {
    "n": "Ingleburn",
    "la": -34.0034,
    "lo": 150.8627,
    "m": 45
  },
  {
    "n": "Minto",
    "la": -34.0327,
    "lo": 150.8454,
    "m": 48
  },
  {
    "n": "Leumeah",
    "la": -34.0492,
    "lo": 150.8377,
    "m": 50
  },
  {
    "n": "Campbelltown",
    "la": -34.067,
    "lo": 150.8147,
    "m": 53
  },
  {
    "n": "Macarthur",
    "la": -34.0728,
    "lo": 150.812,
    "m": 55
  },
  {
    "n": "North Strathfield",
    "la": -33.8616,
    "lo": 151.0883,
    "m": 17
  },
  {
    "n": "Concord West",
    "la": -33.8523,
    "lo": 151.0855,
    "m": 19
  },
  {
    "n": "Rhodes",
    "la": -33.8327,
    "lo": 151.0879,
    "m": 21
  },
  {
    "n": "Meadowbank",
    "la": -33.8189,
    "lo": 151.0908,
    "m": 23
  },
  {
    "n": "West Ryde",
    "la": -33.8074,
    "lo": 151.0884,
    "m": 25
  },
  {
    "n": "Denistone",
    "la": -33.7984,
    "lo": 151.0863,
    "m": 27
  },
  {
    "n": "Eastwood",
    "la": -33.7903,
    "lo": 151.0815,
    "m": 30
  },
  {
    "n": "Epping",
    "la": -33.7714,
    "lo": 151.0824,
    "m": 34
  },
  {
    "n": "Cheltenham",
    "la": -33.7625,
    "lo": 151.0866,
    "m": 36
  },
  {
    "n": "Beecroft",
    "la": -33.7491,
    "lo": 151.0654,
    "m": 38
  },
  {
    "n": "Pennant Hills",
    "la": -33.7398,
    "lo": 151.0721,
    "m": 41
  },
  {
    "n": "Thornleigh",
    "la": -33.7305,
    "lo": 151.0779,
    "m": 43
  },
  {
    "n": "Normanhurst",
    "la": -33.7223,
    "lo": 151.0966,
    "m": 45
  },
  {
    "n": "Quakers Hill",
    "la": -33.7341,
    "lo": 150.8806,
    "m": 55
  },
  {
    "n": "Marayong",
    "la": -33.746,
    "lo": 150.8979,
    "m": 53
  },
  {
    "n": "Schofields",
    "la": -33.7041,
    "lo": 150.8662,
    "m": 60
  },
  {
    "n": "Riverstone",
    "la": -33.6786,
    "lo": 150.8657,
    "m": 65
  },
  {
    "n": "Tallawong",
    "la": -33.692,
    "lo": 150.905,
    "m": 50
  },
  {
    "n": "Rouse Hill",
    "la": -33.681,
    "lo": 150.9125,
    "m": 47
  },
  {
    "n": "Kellyville",
    "la": -33.711,
    "lo": 150.9357,
    "m": 45
  },
  {
    "n": "Bella Vista",
    "la": -33.737,
    "lo": 150.9438,
    "m": 42
  },
  {
    "n": "Norwest",
    "la": -33.7286,
    "lo": 150.9711,
    "m": 40
  },
  {
    "n": "Hills Showground",
    "la": -33.7372,
    "lo": 150.987,
    "m": 38
  },
  {
    "n": "Cherrybrook",
    "la": -33.733,
    "lo": 151.027,
    "m": 35
  },
  {
    "n": "Macquarie Uni",
    "la": -33.7755,
    "lo": 151.1144,
    "m": 25
  },
  {
    "n": "Macquarie Park",
    "la": -33.7768,
    "lo": 151.1252,
    "m": 23
  },
  {
    "n": "North Ryde",
    "la": -33.7878,
    "lo": 151.1273,
    "m": 21
  },
  {
    "n": "Crows Nest",
    "la": -33.8266,
    "lo": 151.2034,
    "m": 11
  },
  {
    "n": "Victoria Cross",
    "la": -33.8403,
    "lo": 151.2076,
    "m": 6
  },
  {
    "n": "Barangaroo",
    "la": -33.8625,
    "lo": 151.2014,
    "m": 1
  },
  {
    "n": "Waterloo",
    "la": -33.9015,
    "lo": 151.2079,
    "m": 8
  },
  {
    "n": "Manly (bus)",
    "la": -33.7989,
    "lo": 151.2853,
    "m": 32
  },
  {
    "n": "Mosman (bus)",
    "la": -33.8275,
    "lo": 151.24,
    "m": 25
  },
  {
    "n": "Dee Why (bus)",
    "la": -33.7536,
    "lo": 151.2856,
    "m": 42
  },
  {
    "n": "Brookvale (bus)",
    "la": -33.767,
    "lo": 151.2731,
    "m": 38
  },
  {
    "n": "Mona Vale (bus)",
    "la": -33.6764,
    "lo": 151.3071,
    "m": 52
  },
  {
    "n": "Coogee (bus)",
    "la": -33.9197,
    "lo": 151.2552,
    "m": 28
  },
  {
    "n": "Maroubra (bus)",
    "la": -33.9476,
    "lo": 151.2402,
    "m": 32
  },
  {
    "n": "Randwick (bus)",
    "la": -33.9173,
    "lo": 151.2398,
    "m": 20
  },
  {
    "n": "Five Dock (bus)",
    "la": -33.8682,
    "lo": 151.1294,
    "m": 18
  },
  {
    "n": "Drummoyne (bus)",
    "la": -33.853,
    "lo": 151.1542,
    "m": 15
  },
  {
    "n": "Castle Hill",
    "la": -33.7325,
    "lo": 151.005,
    "m": 36
  },
  {
    "n": "Marsden Park (bus)",
    "la": -33.685,
    "lo": 150.84,
    "m": 62
  },
  {
    "n": "Ryde (bus)",
    "la": -33.817,
    "lo": 151.108,
    "m": 25
  },
  {
    "n": "Lane Cove (bus)",
    "la": -33.8147,
    "lo": 151.1697,
    "m": 18
  },
  {
    "n": "Frenchs Forest (bus)",
    "la": -33.7556,
    "lo": 151.224,
    "m": 40
  }
]